setup.py
audoai/noise_removal/__init__.py
audoai/noise_removal/noise_removal_client.py
audoai/noise_removal/wav_audio_result.py
audoai_noise_removal.egg-info/PKG-INFO
audoai_noise_removal.egg-info/SOURCES.txt
audoai_noise_removal.egg-info/dependency_links.txt
audoai_noise_removal.egg-info/requires.txt
audoai_noise_removal.egg-info/top_level.txt
test/test_noise_removal_client.py